extras_component/__init__.py
extras_component/frontend/build/asset-manifest.json
extras_component/frontend/build/bootstrap.min.css
extras_component/frontend/build/index.html
extras_component/frontend/build/static/css/main.f43614a0.css
extras_component/frontend/build/static/css/main.f43614a0.css.map
extras_component/frontend/build/static/js/main.1c909a2b.js
extras_component/frontend/build/static/js/main.1c909a2b.js.LICENSE.txt
extras_component/frontend/build/static/js/main.1c909a2b.js.map
nivo_pie_chart-0.0.3.dist-info/LICENSE
nivo_pie_chart-0.0.3.dist-info/METADATA
nivo_pie_chart-0.0.3.dist-info/WHEEL
nivo_pie_chart-0.0.3.dist-info/top_level.txt
nivo_pie_chart-0.0.3.dist-info/RECORD
